tshistory/__init__.py
tshistory/api.py
tshistory/cli.py
tshistory/group.sql
tshistory/migrate.py
tshistory/schema.py
tshistory/schema.sql
tshistory/search.py
tshistory/series.sql
tshistory/storage.py
tshistory/testutil.py
tshistory/tsio.py
tshistory/util.py
tshistory/http/__init__.py
tshistory/http/app.py
tshistory/http/client.py
tshistory/http/horizon.py
tshistory/http/server.py
tshistory/http/util.py
tshistory-0.20.1.dist-info/AUTHORS
tshistory-0.20.1.dist-info/LICENSE
tshistory-0.20.1.dist-info/METADATA
tshistory-0.20.1.dist-info/WHEEL
tshistory-0.20.1.dist-info/entry_points.txt
tshistory-0.20.1.dist-info/top_level.txt
tshistory-0.20.1.dist-info/RECORD
