Metadata-Version: 2.1
Name: tshistory
Version: 0.20.1
Summary: Timeseries store with version control
Home-page: https://hg.sr.ht/~pythonian/tshistory
Author: Pythonian
Author-email: aurelien.campeas@pythonian.fr, arnaud.campeas@pythonian.fr
Classifier: Development Status :: 4 - Beta
Classifier: Intended Audience :: Developers
Classifier: License :: OSI Approved :: GNU Lesser General Public License v3 (LGPLv3)
Classifier: Operating System :: OS Independent
Classifier: Programming Language :: Python :: 3
Classifier: Topic :: Database
Classifier: Topic :: Scientific/Engineering
Classifier: Topic :: Software Development :: Version Control
Requires-Python: >= 3.9
License-File: LICENSE
License-File: AUTHORS
Requires-Dist: simplejson
Requires-Dist: pandas <2.3,>=1.5.3
Requires-Dist: numpy <2
Requires-Dist: dbcache >=0.4.0
Requires-Dist: psyl
Requires-Dist: dateutils
Requires-Dist: sqlalchemy <2
Requires-Dist: sqlhelp
Requires-Dist: click
Requires-Dist: mock
Requires-Dist: inireader
Requires-Dist: pytz
Requires-Dist: tzlocal
Requires-Dist: colorama
Requires-Dist: tqdm
Requires-Dist: flask ==2.3.3
Requires-Dist: flask-restx ==1.3
Requires-Dist: jinja2 <3.2
Requires-Dist: requests
Requires-Dist: version-parser ==1.0.1
Requires-Dist: importlib-metadata ==6.8
Requires-Dist: deprecation
Requires-Dist: requests-auth
